spectator_db-0.0.1.dist-info/licenses/LICENSE
spectatordb/__init__.py
spectatordb/spectatordb.py
spectatordb/connector/__init__.py
spectatordb/connector/sqlite_connector.py
spectatordb/storage/__init__.py
spectatordb/storage/local_storage.py
spectatordb/storage/storage.py
spectator_db-0.0.1.dist-info/METADATA
spectator_db-0.0.1.dist-info/WHEEL
spectator_db-0.0.1.dist-info/top_level.txt
spectator_db-0.0.1.dist-info/RECORD
