Metadata-Version: 2.4
Name: spectator-db
Version: 0.0.1
Summary: A database for storing and managing images and videos.
Author-email: IoT Spectator <shun@formosa1544.com>
License: MIT License
Project-URL: repository, https://github.com/iot-spectator/spectator-db
Requires-Python: >=3.13
License-File: LICENSE
Dynamic: license-file
